refine_task_with_llm/__init__.py
task_refiner_llm-2025.9.92037.dist-info/licenses/LICENSE
task_refiner_llm-2025.9.92037.dist-info/METADATA
task_refiner_llm-2025.9.92037.dist-info/WHEEL
task_refiner_llm-2025.9.92037.dist-info/top_level.txt
task_refiner_llm-2025.9.92037.dist-info/RECORD
