Metadata-Version: 2.4
Name: task_refiner_llm
Version: 2025.9.92037
Summary: Refine unstructured briefs into implementation-ready JSON via LLM7 and llmatch.
Author: Eugene Evstafev
Author-email: hi@eugene.plus
Classifier: Programming Language :: Python :: 3
Classifier: Programming Language :: Python :: 3 :: Only
Classifier: Programming Language :: Python :: 3.11
Classifier: Topic :: Software Development :: Libraries :: Python Modules
Requires-Python: >=3.11
License-File: LICENSE
Dynamic: author
Dynamic: author-email
Dynamic: classifier
Dynamic: description
Dynamic: description-content-type
Dynamic: license-file
Dynamic: requires-python
Dynamic: summary
